{
  "id": "unlogged-days-warning_20260224",
  "title": "Unlogged Days Warning",
  "type": "feature",
  "status": "complete",
  "created": "2026-02-24T00:00:00.000Z",
  "updated": "2026-02-24T03:50:50Z",
  "current_phase": 4,
  "current_task": "4.1",
  "phases": {
    "total": 4,
    "completed": 4
  },
  "tasks": {
    "total": 7,
    "completed": 7
  },
  "commits": [
    "a4bf324: feat(tauri): add unlogged days data hook (unlogged-days-warning_20260224)",
    "79cd88a: chore: mark phase 1 data tasks complete (unlogged-days-warning_20260224)",
    "baa44a8: chore: sync phase 1 metadata state (unlogged-days-warning_20260224)",
    "1c1c7ad: feat(tauri): add log guide modal (unlogged-days-warning_20260224)",
    "d6e5240: feat(tauri): add unlogged days warning banner (unlogged-days-warning_20260224)",
    "2784517: feat(tauri): integrate unlogged warning into main view (unlogged-days-warning_20260224)",
    "4d6330f: feat(tauri): wire unlogged state into tray hook (unlogged-days-warning_20260224)",
    "f14728d: feat(tauri): draw unlogged warning dot on tray icon (unlogged-days-warning_20260224)",
    "b0223ff: feat(tauri): refetch prior weekdays after stop timer (unlogged-days-warning_20260224)",
    "25f1609: chore(tauri): format warning UI and fix reload icon a11y (unlogged-days-warning_20260224)"
  ]
}
